MANIFEST.in
README.md
setup.py
dash_mdlk_components/__init__.py
dash_mdlk_components/bundle.js
dash_mdlk_components/metadata.json
dash_mdlk_components/version.py
dash_mdlk_components.egg-info/PKG-INFO
dash_mdlk_components.egg-info/SOURCES.txt
dash_mdlk_components.egg-info/dependency_links.txt
dash_mdlk_components.egg-info/top_level.txt