Metadata-Version: 1.0
Name: dash-mdlk-components
Version: 0.0.1
Summary: Dash UI components developed by MDLK.
Home-page: UNKNOWN
Author: marcodlk
Author-email: UNKNOWN
License: MIT
Platform: UNKNOWN
